flask_restructuredtext.py
Flask_reStructuredText-1.0.dist-info/top_level.txt
Flask_reStructuredText-1.0.dist-info/METADATA
Flask_reStructuredText-1.0.dist-info/DESCRIPTION.rst
Flask_reStructuredText-1.0.dist-info/metadata.json
Flask_reStructuredText-1.0.dist-info/WHEEL
Flask_reStructuredText-1.0.dist-info/RECORD
