Metadata-Version: 2.0
Name: Flask-reStructuredText
Version: 1.0
Summary: Small extension to make using rst easy
Home-page: http://example.com/flask-sqlite3/
Author: Dennis Fink
Author-email: dennis.fink@c3l.lu
License: BSD
Platform: any
Classifier: Environment :: Web Environment
Classifier: Intended Audience :: Developers
Classifier: License :: OSI Approved :: BSD License
Classifier: Operating System :: OS Independent
Classifier: Programming Language :: Python
Classifier: Topic :: Internet :: WWW/HTTP :: Dynamic Content
Classifier: Topic :: Software Development :: Libraries :: Python Modules
Requires-Dist: Flask
Requires-Dist: docutils
